aws_resources/__init__.py
aws_resources/s3/__init__.py
aws_resources/s3/frontend_origin_bucket.py
14four_infrastructure_control-0.1.1.dist-info/METADATA
14four_infrastructure_control-0.1.1.dist-info/WHEEL
14four_infrastructure_control-0.1.1.dist-info/RECORD
